pyavdb/__init__.py
pyavtools/CIFPObjects.py
pyavtools/Spatial.py
pyavtools/__init__.py
pyavtools/filters.py
pyavtools/scheduler.py
pyavtools/fix/__init__.py
pyavtools/fix/client.py
pyavtools/utils/MakeCIFPIndex.py
pyavtools/utils/__init__.py
pyavui/__init__.py
pyavtools-0.1.0.dist-info/AUTHORS
pyavtools-0.1.0.dist-info/LICENSE
pyavtools-0.1.0.dist-info/METADATA
pyavtools-0.1.0.dist-info/WHEEL
pyavtools-0.1.0.dist-info/entry_points.txt
pyavtools-0.1.0.dist-info/top_level.txt
pyavtools-0.1.0.dist-info/RECORD
