Metadata-Version: 2.1
Name: pyavtools
Version: 0.1.0
Summary: pyAvTools
Home-page: https://github.com/makerplane/pyAvDb
Author: Garrett Herschleb
Author-email: 9.planetary.drive@gmail.com
Classifier: Programming Language :: Python :: 3
Classifier: License :: OSI Approved :: GNU General Public License v2 (GPLv2)
Classifier: Operating System :: POSIX :: Linux
License-File: LICENSE
License-File: AUTHORS
Requires-Dist: pyyaml
Provides-Extra: build
Requires-Dist: build (==0.10.0) ; extra == 'build'
